[
    {
        "zip": "70002",
        "state": "L",
        "customersServed": 11557,
        "customersAffected": 32,
        "lastUpdatedTime": "2025-02-26T21:32:27",
        "latitude": 30.00777,
        "longitude": -90.16195,
        "_loaded_at": "2025-02-26T21:34:06.206878"
    },
    {
        "zip": "70003",
        "state": "L",
        "customersServed": 17846,
        "customersAffected": 19,
        "lastUpdatedTime": "2025-02-26T21:32:27",
        "latitude": 30.00099,
        "longitude": -90.21825,
        "_loaded_at": "2025-02-26T21:34:06.206883"
    },
    {
        "zip": "70086",
        "state": "L",
        "customersServed": 1029,
        "customersAffected": 1,
        "lastUpdatedTime": "2025-02-26T21:32:27",
        "latitude": 30.04259,
        "longitude": -90.85014,
        "_loaded_at": "2025-02-26T21:34:06.206886"
    },
    {
        "zip": "70123",
        "state": "L",
        "customersServed": 16689,
        "customersAffected": 16,
        "lastUpdatedTime": "2025-02-26T21:32:27",
        "latitude": 29.9591,
        "longitude": -90.20393,
        "_loaded_at": "2025-02-26T21:34:06.206889"
    },
    {
        "zip": "70127",
        "state": "L",
        "customersServed": 10641,
        "customersAffected": 1,
        "lastUpdatedTime": "2025-02-26T21:32:27",
        "latitude": 30.03172,
        "longitude": -89.9806,
        "_loaded_at": "2025-02-26T21:34:06.206892"
    },
    {
        "zip": "70129",
        "state": "L",
        "customersServed": 4406,
        "customersAffected": 1,
        "lastUpdatedTime": "2025-02-26T21:32:27",
        "latitude": 30.04602,
        "longitude": -89.89063,
        "_loaded_at": "2025-02-26T21:34:06.206895"
    },
    {
        "zip": "70131",
        "state": "L",
        "customersServed": 11824,
        "customersAffected": 1,
        "lastUpdatedTime": "2025-02-26T21:32:27",
        "latitude": 29.91693,
        "longitude": -89.98767,
        "_loaded_at": "2025-02-26T21:34:06.206897"
    },
    {
        "zip": "70377",
        "state": "L",
        "customersServed": 1896,
        "customersAffected": 1,
        "lastUpdatedTime": "2025-02-26T21:32:27",
        "latitude": 29.46765,
        "longitude": -90.55598,
        "_loaded_at": "2025-02-26T21:34:06.206900"
    },
    {
        "zip": "70391",
        "state": "L",
        "customersServed": 385,
        "customersAffected": 1,
        "lastUpdatedTime": "2025-02-26T21:32:27",
        "latitude": 29.99932,
        "longitude": -91.05772,
        "_loaded_at": "2025-02-26T21:34:06.206902"
    },
    {
        "zip": "70456",
        "state": "L",
        "customersServed": 1314,
        "customersAffected": 29,
        "lastUpdatedTime": "2025-02-26T21:32:27",
        "latitude": 30.76247,
        "longitude": -90.51168,
        "_loaded_at": "2025-02-26T21:34:06.206905"
    },
    {
        "zip": "70462",
        "state": "L",
        "customersServed": 2671,
        "customersAffected": 8,
        "lastUpdatedTime": "2025-02-26T21:32:27",
        "latitude": 30.38636,
        "longitude": -90.58355,
        "_loaded_at": "2025-02-26T21:34:06.206907"
    },
    {
        "zip": "70543",
        "state": "L",
        "customersServed": 787,
        "customersAffected": 9,
        "lastUpdatedTime": "2025-02-26T21:32:27",
        "latitude": 30.3335,
        "longitude": -92.49629,
        "_loaded_at": "2025-02-26T21:34:06.206909"
    },
    {
        "zip": "70546",
        "state": "L",
        "customersServed": 6305,
        "customersAffected": 4,
        "lastUpdatedTime": "2025-02-26T21:32:27",
        "latitude": 30.23529,
        "longitude": -92.65886,
        "_loaded_at": "2025-02-26T21:34:06.206912"
    },
    {
        "zip": "70560",
        "state": "L",
        "customersServed": 5224,
        "customersAffected": 1,
        "lastUpdatedTime": "2025-02-26T21:32:27",
        "latitude": 29.98533,
        "longitude": -91.84989,
        "_loaded_at": "2025-02-26T21:34:06.206914"
    },
    {
        "zip": "70601",
        "state": "L",
        "customersServed": 17810,
        "customersAffected": 1,
        "lastUpdatedTime": "2025-02-26T21:32:27",
        "latitude": 30.2245,
        "longitude": -93.20581,
        "_loaded_at": "2025-02-26T21:34:06.206917"
    },
    {
        "zip": "70605",
        "state": "L",
        "customersServed": 19848,
        "customersAffected": 3,
        "lastUpdatedTime": "2025-02-26T21:32:27",
        "latitude": 30.16871,
        "longitude": -93.24532,
        "_loaded_at": "2025-02-26T21:34:06.206919"
    },
    {
        "zip": "70615",
        "state": "L",
        "customersServed": 6102,
        "customersAffected": 1,
        "lastUpdatedTime": "2025-02-26T21:32:27",
        "latitude": 30.24389,
        "longitude": -93.15242,
        "_loaded_at": "2025-02-26T21:34:06.206922"
    },
    {
        "zip": "70669",
        "state": "L",
        "customersServed": 4391,
        "customersAffected": 1,
        "lastUpdatedTime": "2025-02-26T21:32:27",
        "latitude": 30.25888,
        "longitude": -93.2663,
        "_loaded_at": "2025-02-26T21:34:06.206925"
    },
    {
        "zip": "70734",
        "state": "L",
        "customersServed": 3891,
        "customersAffected": 6,
        "lastUpdatedTime": "2025-02-26T21:32:27",
        "latitude": 30.24782,
        "longitude": -91.00128,
        "_loaded_at": "2025-02-26T21:34:06.206927"
    },
    {
        "zip": "70767",
        "state": "L",
        "customersServed": 7517,
        "customersAffected": 11,
        "lastUpdatedTime": "2025-02-26T21:32:27",
        "latitude": 30.48924,
        "longitude": -91.26587,
        "_loaded_at": "2025-02-26T21:34:06.206930"
    },
    {
        "zip": "70769",
        "state": "L",
        "customersServed": 13717,
        "customersAffected": 1,
        "lastUpdatedTime": "2025-02-26T21:32:27",
        "latitude": 30.31139,
        "longitude": -90.94418,
        "_loaded_at": "2025-02-26T21:34:06.206932"
    },
    {
        "zip": "70809",
        "state": "L",
        "customersServed": 15875,
        "customersAffected": 1,
        "lastUpdatedTime": "2025-02-26T21:32:27",
        "latitude": 30.39812,
        "longitude": -91.07447,
        "_loaded_at": "2025-02-26T21:34:06.206935"
    },
    {
        "zip": "70812",
        "state": "L",
        "customersServed": 3748,
        "customersAffected": 38,
        "lastUpdatedTime": "2025-02-26T21:32:27",
        "latitude": 30.50383,
        "longitude": -91.11509,
        "_loaded_at": "2025-02-26T21:34:06.206937"
    },
    {
        "zip": "71068",
        "state": "L",
        "customersServed": 1032,
        "customersAffected": 1,
        "lastUpdatedTime": "2025-02-26T21:32:27",
        "latitude": 32.30945,
        "longitude": -93.30347,
        "_loaded_at": "2025-02-26T21:34:06.206939"
    },
    {
        "zip": "71203",
        "state": "L",
        "customersServed": 19250,
        "customersAffected": 6,
        "lastUpdatedTime": "2025-02-26T21:32:27",
        "latitude": 32.5353,
        "longitude": -92.04635,
        "_loaded_at": "2025-02-26T21:34:06.206942"
    },
    {
        "zip": "71226",
        "state": "L",
        "customersServed": 1318,
        "customersAffected": 15,
        "lastUpdatedTime": "2025-02-26T21:32:27",
        "latitude": 32.29189,
        "longitude": -92.4826,
        "_loaded_at": "2025-02-26T21:34:06.206944"
    },
    {
        "zip": "71261",
        "state": "L",
        "customersServed": 1354,
        "customersAffected": 1,
        "lastUpdatedTime": "2025-02-26T21:32:27",
        "latitude": 32.7641,
        "longitude": -91.72512,
        "_loaded_at": "2025-02-26T21:34:06.206947"
    },
    {
        "zip": "71410",
        "state": "L",
        "customersServed": 148,
        "customersAffected": 1,
        "lastUpdatedTime": "2025-02-26T21:32:27",
        "latitude": 31.96569,
        "longitude": -92.7773,
        "_loaded_at": "2025-02-26T21:34:06.206949"
    },
    {
        "zip": "OTHER",
        "state": "L",
        "customersServed": 2,
        "customersAffected": 2,
        "lastUpdatedTime": "2025-02-26T21:32:27",
        "latitude": null,
        "longitude": null,
        "_loaded_at": "2025-02-26T21:34:06.206952"
    }
]