[
    {
        "zip": "70003",
        "state": "L",
        "customersServed": 17438,
        "customersAffected": 1,
        "lastUpdatedTime": "2023-03-13T23:20:32",
        "latitude": 30.00099,
        "longitude": -90.21825,
        "_loaded_at": "2023-03-13T23:22:09.052149"
    },
    {
        "zip": "70037",
        "state": "L",
        "customersServed": 7417,
        "customersAffected": 1,
        "lastUpdatedTime": "2023-03-13T23:20:32",
        "latitude": 29.82797,
        "longitude": -90.00612,
        "_loaded_at": "2023-03-13T23:22:09.052156"
    },
    {
        "zip": "70049",
        "state": "L",
        "customersServed": 1009,
        "customersAffected": 245,
        "lastUpdatedTime": "2023-03-13T23:20:32",
        "latitude": 30.04645,
        "longitude": -90.56182,
        "_loaded_at": "2023-03-13T23:22:09.052160"
    },
    {
        "zip": "70084",
        "state": "L",
        "customersServed": 3080,
        "customersAffected": 5,
        "lastUpdatedTime": "2023-03-13T23:20:32",
        "latitude": 30.05773,
        "longitude": -90.55943,
        "_loaded_at": "2023-03-13T23:22:09.052165"
    },
    {
        "zip": "70085",
        "state": "L",
        "customersServed": 2850,
        "customersAffected": 1,
        "lastUpdatedTime": "2023-03-13T23:20:32",
        "latitude": 29.87148,
        "longitude": -89.83376,
        "_loaded_at": "2023-03-13T23:22:09.052169"
    },
    {
        "zip": "70086",
        "state": "L",
        "customersServed": 1023,
        "customersAffected": 94,
        "lastUpdatedTime": "2023-03-13T23:20:32",
        "latitude": 30.04259,
        "longitude": -90.85014,
        "_loaded_at": "2023-03-13T23:22:09.052173"
    },
    {
        "zip": "70090",
        "state": "L",
        "customersServed": 3453,
        "customersAffected": 1256,
        "lastUpdatedTime": "2023-03-13T23:20:32",
        "latitude": 29.97604,
        "longitude": -90.69946,
        "_loaded_at": "2023-03-13T23:22:09.052178"
    },
    {
        "zip": "70114",
        "state": "L",
        "customersServed": 10996,
        "customersAffected": 1,
        "lastUpdatedTime": "2023-03-13T23:20:32",
        "latitude": 29.93201,
        "longitude": -90.02746,
        "_loaded_at": "2023-03-13T23:22:09.052182"
    },
    {
        "zip": "70115",
        "state": "L",
        "customersServed": 20222,
        "customersAffected": 2,
        "lastUpdatedTime": "2023-03-13T23:20:32",
        "latitude": 29.92749,
        "longitude": -90.09866,
        "_loaded_at": "2023-03-13T23:22:09.052186"
    },
    {
        "zip": "70131",
        "state": "L",
        "customersServed": 11763,
        "customersAffected": 2,
        "lastUpdatedTime": "2023-03-13T23:20:32",
        "latitude": 29.91693,
        "longitude": -89.98767,
        "_loaded_at": "2023-03-13T23:22:09.052191"
    },
    {
        "zip": "70401",
        "state": "L",
        "customersServed": 11791,
        "customersAffected": 9,
        "lastUpdatedTime": "2023-03-13T23:20:32",
        "latitude": 30.52107,
        "longitude": -90.47426,
        "_loaded_at": "2023-03-13T23:22:09.052195"
    },
    {
        "zip": "70403",
        "state": "L",
        "customersServed": 14693,
        "customersAffected": 1,
        "lastUpdatedTime": "2023-03-13T23:20:32",
        "latitude": 30.48397,
        "longitude": -90.47833,
        "_loaded_at": "2023-03-13T23:22:09.052200"
    },
    {
        "zip": "70454",
        "state": "L",
        "customersServed": 16258,
        "customersAffected": 6,
        "lastUpdatedTime": "2023-03-13T23:20:32",
        "latitude": 30.44136,
        "longitude": -90.42073,
        "_loaded_at": "2023-03-13T23:22:09.052204"
    },
    {
        "zip": "70462",
        "state": "L",
        "customersServed": 2555,
        "customersAffected": 809,
        "lastUpdatedTime": "2023-03-13T23:20:32",
        "latitude": 30.38636,
        "longitude": -90.58355,
        "_loaded_at": "2023-03-13T23:22:09.052209"
    },
    {
        "zip": "70517",
        "state": "L",
        "customersServed": 2276,
        "customersAffected": 29,
        "lastUpdatedTime": "2023-03-13T23:20:32",
        "latitude": 30.28614,
        "longitude": -91.88271,
        "_loaded_at": "2023-03-13T23:22:09.052213"
    },
    {
        "zip": "70601",
        "state": "L",
        "customersServed": 17011,
        "customersAffected": 68,
        "lastUpdatedTime": "2023-03-13T23:20:32",
        "latitude": 30.2245,
        "longitude": -93.20581,
        "_loaded_at": "2023-03-13T23:22:09.052217"
    },
    {
        "zip": "70706",
        "state": "L",
        "customersServed": 438,
        "customersAffected": 10,
        "lastUpdatedTime": "2023-03-13T23:20:32",
        "latitude": 30.59262,
        "longitude": -90.93751,
        "_loaded_at": "2023-03-13T23:22:09.052221"
    },
    {
        "zip": "70774",
        "state": "L",
        "customersServed": 1025,
        "customersAffected": 1,
        "lastUpdatedTime": "2023-03-13T23:20:32",
        "latitude": 30.23919,
        "longitude": -90.83908,
        "_loaded_at": "2023-03-13T23:22:09.052226"
    },
    {
        "zip": "70810",
        "state": "L",
        "customersServed": 20913,
        "customersAffected": 1,
        "lastUpdatedTime": "2023-03-13T23:20:32",
        "latitude": 30.36238,
        "longitude": -91.08926,
        "_loaded_at": "2023-03-13T23:22:09.052230"
    },
    {
        "zip": "70815",
        "state": "L",
        "customersServed": 12539,
        "customersAffected": 1,
        "lastUpdatedTime": "2023-03-13T23:20:32",
        "latitude": 30.45703,
        "longitude": -91.06799,
        "_loaded_at": "2023-03-13T23:22:09.052235"
    },
    {
        "zip": "71245",
        "state": "L",
        "customersServed": 1266,
        "customersAffected": 1,
        "lastUpdatedTime": "2023-03-13T23:20:32",
        "latitude": 32.52538,
        "longitude": -92.71358,
        "_loaded_at": "2023-03-13T23:22:09.052239"
    },
    {
        "zip": "71254",
        "state": "L",
        "customersServed": 2806,
        "customersAffected": 1,
        "lastUpdatedTime": "2023-03-13T23:20:32",
        "latitude": 32.78481,
        "longitude": -91.23093,
        "_loaded_at": "2023-03-13T23:22:09.052243"
    },
    {
        "zip": "71280",
        "state": "L",
        "customersServed": 2535,
        "customersAffected": 1,
        "lastUpdatedTime": "2023-03-13T23:20:32",
        "latitude": 32.69345,
        "longitude": -92.07497,
        "_loaded_at": "2023-03-13T23:22:09.052248"
    },
    {
        "zip": "OTHER",
        "state": "L",
        "customersServed": 3,
        "customersAffected": 3,
        "lastUpdatedTime": "2023-03-13T23:20:32",
        "latitude": null,
        "longitude": null,
        "_loaded_at": "2023-03-13T23:22:09.052252"
    }
]