[
    {
        "zip": "70043",
        "state": "L",
        "customersServed": 10109,
        "customersAffected": 1,
        "lastUpdatedTime": "2022-11-10T10:22:32",
        "latitude": 29.94597,
        "longitude": -89.96388,
        "_loaded_at": "2022-11-10T10:24:33.488573"
    },
    {
        "zip": "70454",
        "state": "L",
        "customersServed": 16102,
        "customersAffected": 1,
        "lastUpdatedTime": "2022-11-10T10:22:32",
        "latitude": 30.44136,
        "longitude": -90.42073,
        "_loaded_at": "2022-11-10T10:24:33.488580"
    },
    {
        "zip": "70601",
        "state": "L",
        "customersServed": 16971,
        "customersAffected": 168,
        "lastUpdatedTime": "2022-11-10T10:22:32",
        "latitude": 30.2245,
        "longitude": -93.20581,
        "_loaded_at": "2022-11-10T10:24:33.488585"
    },
    {
        "zip": "70602",
        "state": "L",
        "customersServed": 49,
        "customersAffected": 1,
        "lastUpdatedTime": "2022-11-10T10:22:32",
        "latitude": 30.22645,
        "longitude": -93.21335,
        "_loaded_at": "2022-11-10T10:24:33.488590"
    },
    {
        "zip": "70605",
        "state": "L",
        "customersServed": 18792,
        "customersAffected": 1,
        "lastUpdatedTime": "2022-11-10T10:22:32",
        "latitude": 30.16871,
        "longitude": -93.24532,
        "_loaded_at": "2022-11-10T10:24:33.488594"
    },
    {
        "zip": "70802",
        "state": "L",
        "customersServed": 12076,
        "customersAffected": 1,
        "lastUpdatedTime": "2022-11-10T10:22:32",
        "latitude": 30.44612,
        "longitude": -91.1716,
        "_loaded_at": "2022-11-10T10:24:33.488599"
    },
    {
        "zip": "70817",
        "state": "L",
        "customersServed": 11741,
        "customersAffected": 1,
        "lastUpdatedTime": "2022-11-10T10:22:32",
        "latitude": 30.38227,
        "longitude": -91.00252,
        "_loaded_at": "2022-11-10T10:24:33.488604"
    },
    {
        "zip": "71202",
        "state": "L",
        "customersServed": 10671,
        "customersAffected": 6,
        "lastUpdatedTime": "2022-11-10T10:22:32",
        "latitude": 32.44317,
        "longitude": -92.09124,
        "_loaded_at": "2022-11-10T10:24:33.488608"
    },
    {
        "zip": "71371",
        "state": "L",
        "customersServed": 887,
        "customersAffected": 1,
        "lastUpdatedTime": "2022-11-10T10:22:32",
        "latitude": 31.67793,
        "longitude": -92.23311,
        "_loaded_at": "2022-11-10T10:24:33.488613"
    },
    {
        "zip": "71373",
        "state": "L",
        "customersServed": 1163,
        "customersAffected": 2,
        "lastUpdatedTime": "2022-11-10T10:22:32",
        "latitude": 31.56768,
        "longitude": -91.4838,
        "_loaded_at": "2022-11-10T10:24:33.488618"
    },
    {
        "zip": "71483",
        "state": "L",
        "customersServed": 2430,
        "customersAffected": 1,
        "lastUpdatedTime": "2022-11-10T10:22:32",
        "latitude": 31.91955,
        "longitude": -92.647,
        "_loaded_at": "2022-11-10T10:24:33.488622"
    },
    {
        "zip": "OTHER",
        "state": "L",
        "customersServed": 6,
        "customersAffected": 6,
        "lastUpdatedTime": "2022-11-10T10:22:32",
        "latitude": null,
        "longitude": null,
        "_loaded_at": "2022-11-10T10:24:33.488627"
    }
]