[
    {
        "zip": "70001",
        "state": "L",
        "customersServed": 20781,
        "customersAffected": 1,
        "lastUpdatedTime": "2022-10-21T09:42:32",
        "latitude": 29.98965,
        "longitude": -90.1698,
        "_loaded_at": "2022-10-21T09:44:18.055805"
    },
    {
        "zip": "70002",
        "state": "L",
        "customersServed": 11263,
        "customersAffected": 6,
        "lastUpdatedTime": "2022-10-21T09:42:32",
        "latitude": 30.00777,
        "longitude": -90.16195,
        "_loaded_at": "2022-10-21T09:44:18.055813"
    },
    {
        "zip": "70084",
        "state": "L",
        "customersServed": 3092,
        "customersAffected": 1,
        "lastUpdatedTime": "2022-10-21T09:42:32",
        "latitude": 30.05773,
        "longitude": -90.55943,
        "_loaded_at": "2022-10-21T09:44:18.055818"
    },
    {
        "zip": "70601",
        "state": "L",
        "customersServed": 17014,
        "customersAffected": 2,
        "lastUpdatedTime": "2022-10-21T09:42:32",
        "latitude": 30.2245,
        "longitude": -93.20581,
        "_loaded_at": "2022-10-21T09:44:18.055823"
    }
]