[
    {
        "zip": "70006",
        "state": "L",
        "customersServed": 7795,
        "customersAffected": 1,
        "lastUpdatedTime": "2022-07-28T05:44:32",
        "latitude": 30.01338,
        "longitude": -90.18868,
        "_loaded_at": "2022-07-28T05:45:40.359969"
    },
    {
        "zip": "70058",
        "state": "L",
        "customersServed": 17822,
        "customersAffected": 3,
        "lastUpdatedTime": "2022-07-28T05:44:32",
        "latitude": 29.87429,
        "longitude": -90.06389,
        "_loaded_at": "2022-07-28T05:45:40.359976"
    },
    {
        "zip": "70119",
        "state": "L",
        "customersServed": 22229,
        "customersAffected": 2,
        "lastUpdatedTime": "2022-07-28T05:44:32",
        "latitude": 29.97603,
        "longitude": -90.08831,
        "_loaded_at": "2022-07-28T05:45:40.359981"
    },
    {
        "zip": "70122",
        "state": "L",
        "customersServed": 16804,
        "customersAffected": 1,
        "lastUpdatedTime": "2022-07-28T05:44:32",
        "latitude": 30.00593,
        "longitude": -90.06174,
        "_loaded_at": "2022-07-28T05:45:40.359986"
    },
    {
        "zip": "70128",
        "state": "L",
        "customersServed": 7383,
        "customersAffected": 1,
        "lastUpdatedTime": "2022-07-28T05:44:32",
        "latitude": 30.04885,
        "longitude": -89.95628,
        "_loaded_at": "2022-07-28T05:45:40.359991"
    },
    {
        "zip": "70130",
        "state": "L",
        "customersServed": 10174,
        "customersAffected": 4,
        "lastUpdatedTime": "2022-07-28T05:44:32",
        "latitude": 29.94423,
        "longitude": -90.07154,
        "_loaded_at": "2022-07-28T05:45:40.359995"
    },
    {
        "zip": "70810",
        "state": "L",
        "customersServed": 21016,
        "customersAffected": 2,
        "lastUpdatedTime": "2022-07-28T05:44:32",
        "latitude": 30.36238,
        "longitude": -91.08926,
        "_loaded_at": "2022-07-28T05:45:40.360000"
    },
    {
        "zip": "70814",
        "state": "L",
        "customersServed": 4948,
        "customersAffected": 2,
        "lastUpdatedTime": "2022-07-28T05:44:32",
        "latitude": 30.4824,
        "longitude": -91.07228,
        "_loaded_at": "2022-07-28T05:45:40.360004"
    },
    {
        "zip": "70820",
        "state": "L",
        "customersServed": 11160,
        "customersAffected": 1,
        "lastUpdatedTime": "2022-07-28T05:44:32",
        "latitude": 30.37751,
        "longitude": -91.16381,
        "_loaded_at": "2022-07-28T05:45:40.360009"
    },
    {
        "zip": "71235",
        "state": "L",
        "customersServed": 2032,
        "customersAffected": 1,
        "lastUpdatedTime": "2022-07-28T05:44:32",
        "latitude": 32.70061,
        "longitude": -92.65658,
        "_loaded_at": "2022-07-28T05:45:40.360014"
    },
    {
        "zip": "OTHER",
        "state": "L",
        "customersServed": 2,
        "customersAffected": 2,
        "lastUpdatedTime": "2022-07-28T05:44:32",
        "latitude": null,
        "longitude": null,
        "_loaded_at": "2022-07-28T05:45:40.360018"
    }
]